enaml_extensions-0.4.4.data/data/LICENSE
enaml_extensions-0.4.4.dist-info/licenses/AUTHORS
enaml_extensions-0.4.4.dist-info/licenses/LICENSE
enamlext/__init__.py
enamlext/_version.py
enamlext/atom.py
enamlext/view_model.py
enamlext/auto/__init__.py
enamlext/auto/_editor.py
enamlext/auto/tests/__init__.py
enamlext/auto/tests/__todo_test_editor.py
enamlext/core/__init__.py
enamlext/qt/__init__.py
enamlext/qt/qt_dataframe.py
enamlext/qt/qt_font_combo_box.py
enamlext/qt/qt_star.py
enamlext/qt/qt_table.py
enamlext/qt/qt_traffic_light.py
enamlext/qt/qtable.py
enamlext/qt/table/__init__.py
enamlext/qt/table/column.py
enamlext/qt/table/defs.py
enamlext/qt/table/filtering.py
enamlext/qt/table/summary.py
enamlext/qt/table/table_context.py
enamlext/widgets/__init__.py
enamlext/widgets/_shortcuts.py
enamlext/widgets/_text_input_dialog.enaml
enamlext/widgets/checklist.enaml
enamlext/widgets/color_button.enaml
enamlext/widgets/dataframe.enaml
enamlext/widgets/dialogs.enaml
enamlext/widgets/dict_view.enaml
enamlext/widgets/field.py
enamlext/widgets/font_combo_box.py
enamlext/widgets/gradient_label.enaml
enamlext/widgets/ipython_console.enaml
enamlext/widgets/json_editor.enaml
enamlext/widgets/link_label.enaml
enamlext/widgets/multi_select_dialog.enaml
enamlext/widgets/multi_select_model.py
enamlext/widgets/notebook.enaml
enamlext/widgets/star.py
enamlext/widgets/table.py
enamlext/widgets/traffic_light.py
enaml_extensions-0.4.4.dist-info/METADATA
enaml_extensions-0.4.4.dist-info/WHEEL
enaml_extensions-0.4.4.dist-info/top_level.txt
enaml_extensions-0.4.4.dist-info/RECORD
