Metadata-Version: 2.4
Name: enaml-extensions
Version: 0.4.4
Summary: Extra widgets and extensions for building UIs with Enaml
Home-page: http://github.com/gabrielcnr/enaml-extensions
Author: Gabriel Reis
Author-email: gabrielcnr@gmail.com
License: LGPL
Keywords: enaml qt widgets extras extensions table qt-table ui gui
Classifier: Intended Audience :: Developers
Classifier: License :: OSI Approved :: GNU Lesser General Public License v3 (LGPLv3)
Classifier: Operating System :: OS Independent
Classifier: Programming Language :: Python :: 3
Classifier: Programming Language :: Python :: 3.10
Classifier: Programming Language :: Python :: 3.11
Classifier: Programming Language :: Python :: 3.12
Classifier: Programming Language :: Python :: 3.13
Classifier: Topic :: Desktop Environment :: Window Managers
Classifier: Topic :: Software Development :: User Interfaces
Classifier: Topic :: Software Development :: Widget Sets
Requires: enaml
Requires-Python: >=3.10
License-File: LICENSE
License-File: AUTHORS
Requires-Dist: enaml
Requires-Dist: QScintilla
Requires-Dist: pip
Requires-Dist: qtpy
Requires-Dist: numpy
Provides-Extra: testing
Requires-Dist: pytest; extra == "testing"
Requires-Dist: pytest-mock; extra == "testing"
Requires-Dist: pytest-qt; extra == "testing"
Requires-Dist: pandas; extra == "testing"
Dynamic: author
Dynamic: author-email
Dynamic: classifier
Dynamic: description
Dynamic: description-content-type
Dynamic: home-page
Dynamic: keywords
Dynamic: license
Dynamic: license-file
Dynamic: provides-extra
Dynamic: requires
Dynamic: requires-dist
Dynamic: requires-python
Dynamic: summary
